setup.py
common/__init__.py
common/delog.py
common/metas.py
common/utils.py
common/variables.py
gvg_mess_srv.egg-info/PKG-INFO
gvg_mess_srv.egg-info/SOURCES.txt
gvg_mess_srv.egg-info/dependency_links.txt
gvg_mess_srv.egg-info/requires.txt
gvg_mess_srv.egg-info/top_level.txt
server/__init__.py
server/db_man.py
server/descs.py
server/srv_add_user.py
server/srv_del_user.py
server/srv_gui.py
server/srv_sck.py
unit_tests/__init__.py
unit_tests/test_client.py
unit_tests/test_server.py
unit_tests/test_utils.py